byebase/__init__.py
byebase/byebase_conf.py
byebase/adapters/__init__.py
byebase/adapters/amqp_notification.py
byebase/adapters/elasticsearch.py
byebase/helpers/__init__.py
byebase/helpers/file_helper.py
byebase/helpers/gstorage_helper.py
byebase/utils/__init__.py
byebase/utils/logging.py
byebase-0.0.1.dist-info/METADATA
byebase-0.0.1.dist-info/WHEEL
byebase-0.0.1.dist-info/top_level.txt
byebase-0.0.1.dist-info/RECORD
